claudecli/__init__.py
claudecli/cli.py
claudecli/core.py
claudecli/logger.py
claudecli-0.1.0rc3.dist-info/LICENSE
claudecli-0.1.0rc3.dist-info/METADATA
claudecli-0.1.0rc3.dist-info/WHEEL
claudecli-0.1.0rc3.dist-info/entry_points.txt
claudecli-0.1.0rc3.dist-info/RECORD
