Metadata-Version: 2.1
Name: claudecli
Version: 0.1.0rc3
Summary: Natural language interface for command line using Claude AI
Home-page: https://github.com/ndamulelonemakh/claudecli
License: MIT
Keywords: cli,claude,ai,shell,automation
Author: Ndamulelo Nemakhavhani
Author-email: info@rihonegroup.com
Requires-Python: >=3.10,<4.0
Classifier: Intended Audience :: Developers
Classifier: License :: OSI Approved :: MIT License
Classifier: Programming Language :: Python :: 3
Classifier: Programming Language :: Python :: 3.10
Classifier: Programming Language :: Python :: 3.11
Classifier: Programming Language :: Python :: 3.12
Classifier: Topic :: Security
Requires-Dist: anthropic (>=0.39.0,<0.40.0)
Requires-Dist: click (>=8.1.7,<9.0.0)
Project-URL: Repository, https://github.com/ndamulelonemakh/claude-cli#README
